{"vicennial":1527.33,"Nson":1164.49,"n1k1_tos1_na":1741.0,"yangshuang":954.48,"kenenalmat":1731.41,"Jeffrey":1707.74,"naagi":1915.74,"PbTfcLx":2049.68,"desik":1383.15,"kunalk":1374.0,"smallcattom":1226.32,"dhirajfx3":1437.55,"pipengtan":2105.84,"zyz3_14":1157.0,"hagyu_aya":1220.68,"yuchiki":1239.09,"harumeki":651.04,"takakuwa2":2097.0,"XzzF":1066.17,"qianqian":1518.24,"mayumini":1161.13,"Khang":1379.21,"mohit_97":1012.0,"bttb":936.89,"SumerSao":1285.0,"terakun":1127.51,"venkat1997":1549.0,"bcools":1225.0,"acguy":1463.47,"atulhjp":1213.73,"zzulisll":1225.21,"tanruidd":1223.29,"nmjiri":1202.06,"raja1999":1283.36,"rizhiy":1089.48,"abreto":1369.05,"Momochi":517.16,"fr0st":1596.11,"yuxifan":1355.0,"mori08":1382.65,"hirata0517masato":1202.63,"hayabusa104":1349.41,"university":1151.19,"shi2chuan1":1182.89,"warm4C0":1182.89,"jdh":1315.49,"shanin":1322.0,"yigarashi":1395.99,"sakaki":1323.94,"plcherrim":1045.07,"kurokoji":1152.69,"feybk":851.21,"AVM_Martin":1799.0,"Microbe":826.84,"sahuang":1366.01,"shimisho":1188.59,"amber":1065.57,"junjunjunk":920.06,"phanta_stick":1016.5,"nicklaw296":1337.42,"dicenull":1038.4,"rui0422":895.39,"kory271":1239.78,"hiziri":1099.79,"mayoi":767.0,"SugarDragon5":1264.88,"koda0631":967.48,"Zoedexinzhuang":855.91,"Ronly":1164.63,"katakana1818":1204.29,"tuquanrong":1171.89,"kjnh10":1306.23,"pytran":1188.96,"hogeki":1071.63,"sa8":1248.26,"takatowin":1062.0,"higucheese":1242.59,"kawamura2001":1012.82,"ykarako":909.44,"shake":979.17,"alttkymmm":1191.28,"umireon":564.86,"stkz_uq":891.12,"ophelia":1241.79,"Electron_A":1235.02,"hhelibex":1190.81,"Gfy593L3":1078.33,"tanimura":685.79,"mizutoki_":888.64,"th90tk297":1047.87,"kuretchi":1182.33,"NKT":1095.4,"umisan":983.68,"yumsiim":1242.37,"rayhotate":953.65,"tut_tut":844.27,"easyhoon":508.53,"aetenotanaka":891.26,"hataro":436.0,"tome100100":924.16,"numkn644":673.7,"hnust_LHQ":794.0,"whileD":862.46,"albicilla":1150.28,"Kirin0890":777.94,"adi001":1090.6,"Agodoriru":516.27,"yyy01":1019.35,"agw02010":761.7,"idon":1035.07,"iry":930.68,"shiba24":1331.73,"yangyuting1225":1258.04,"amtgjw":614.58,"sunaemon":1084.56,"b1464296":1074.97,"cmjb":1267.53,"unbelievable":1126.09,"lavender730":649.04,"Data_Lier_LS":624.84,"himkt":842.41,"naksh9619":1234.55,"aaadmy":805.31,"oysuake":939.21,"f_t_ikt":853.81,"jun87":1179.41,"tripdancer1989":1023.2,"kilattoeruru":991.68,"notenoughmana":937.13,"machibito2":965.49,"taku7756":728.78,"alphaKAI":829.06,"Hewla":1229.58,"wheson":1030.75,"crevette":720.79,"keidaroo":1001.47,"alex00":1107.36,"cse_nazmul":783.14,"zzq_cpp":934.72,"dwhdwh":902.34,"calmery":638.95,"aim_cpo":893.38,"takayan4":810.26,"NiEnIe":700.69,"delta71":976.42,"imbabao":961.0,"Lilly":983.04,"zzuzayu":1309.0,"shirahata":663.68,"xztaityozx":1005.88,"solighta":1599.0,"JAkatsubaki":541.63,"oshiumi":1202.24,"utam0k":1009.72,"do2424":814.03,"aimy":1321.29,"moxtsuan":1015.49,"inaba3":1016.95,"BurnEtz":914.58,"miki":1150.24,"imait":715.11,"tettchan":810.71,"himajin008":987.47,"naobird":869.38,"tancahn2380":1098.05,"t0123":843.86,"Lenivec_lenivyj":853.0,"ameyanator":930.0,"ohnabe":780.66,"snowfoxy":1122.92,"wariuni":878.86,"heve":475.0,"zfr123":228.93,"yata":904.47,"zwu2016011075":916.41,"Amour":348.95,"kezawa":436.0,"tomsyd":586.95,"Pl4gue":827.74,"fegi":1040.84,"meitel1014":732.46,"tone_back":1226.92,"noriok":914.09,"honebone":867.06,"yejunjie":-97.79,"sanchay123":855.97,"mkan_0141":1028.98,"XImenau":436.0,"marumtr2016":709.31,"p_8ty":903.29,"tks3141":500.0,"mencotton":1133.38,"pdfxy":1314.85,"SmallSir":1003.09,"GYD3462508929":634.0,"wanidon":954.22,"shumy":915.67,"blacknoodle":942.05,"FockSpace":936.67,"Bantako":863.31,"yuno_miyako":1252.0,"KeitaKishida0811":973.93,"kantohm11":1008.69,"kns330":708.97,"solver9999":712.02,"Hitomichan":931.15,"fromT":624.42,"abc1310054026":216.84,"deraken":967.98,"Masumi":565.58,"mk10":782.67,"T_NABA":1026.79,"acmer":383.0,"david":711.55,"ravie403":1027.27,"patybo":800.0,"piro77":823.67,"keimy":738.09,"ueyuki":-215.0,"I_am_stupid":1217.79,"AT274":783.58,"urumeiwashi":1010.5,"yamarten":696.0,"prd_xxx":1285.35,"iroha168":1150.33,"siiiec":744.0,"ashubeckham":952.82,"jieyijie":162.68,"crampon231":1038.0,"y_taira_c":1050.0,"otoan_ikuzus":737.35,"musaprg":622.93,"sca1l":979.78,"justinkoh80":597.84,"aaakirito":368.0,"neetsdkasu":1047.6,"srisiro":468.95,"masakt":690.21,"neo_wata":363.11,"mmura":1003.63,"ihlbbfbtr":906.89,"Starry_sky":880.01,"magicalinnet":432.52,"gunner_1696":906.72,"m0bec":810.22,"TSNEZHJ":957.74,"nishuting":223.0,"pocket":977.3,"reverd":666.37,"Sen":823.05,"zwuwuyifeng":88.0,"tassi":702.0,"zxy2016011117":178.47,"ZZU20152430244":1603.0,"xhc2016011050":719.09,"yaya1026":899.64,"areku2014":307.17,"nar930":861.0,"kgarun":39.0,"lovemejj":941.42,"taisa_tk":542.21,"mikoi":367.0,"reiji1112":1221.63,"fumino":1057.45,"YDK":759.97,"zjc11151921":155.0,"smartgoods":703.7,"marukakko":558.44,"Nossi":730.0,"time504":237.11,"shumon_84":869.0,"yafbf07e5961f51":498.0,"y_yujin":388.21,"norimiso":1042.8,"xofyd1857":480.18,"tencha":546.78,"k16180":171.95,"swkfn":342.37,"irobe_sama":430.92,"geo_partner":448.26,"chaojidage":826.46,"tiginkgo":1007.15,"qAD4KyEhlG":358.32,"ggl162":462.73,"fusheng":228.84,"wang563681252":895.12,"romansp":1343.0,"motaleb_ICT":305.47,"mosmos21":1047.6,"Amnestia":607.55,"jon2240":918.42,"jasamdobro":1183.51,"pasta_az":909.26,"sira":1117.54,"Takeno_hito":775.25,"narita":1115.9,"Hirosesesese23":882.97,"HDDbreaker":685.14,"IKKO_Ohta":643.51,"Skyler_":1269.84,"ibuki2003":848.58,"namayaki":896.62,"izumin5210":1506.18,"Remonmaru0926":672.5,"ryuboku":770.22,"zuvizudar":423.01,"nacl_crystal":965.0,"libra9z":877.25,"nekokan":4.0,"onyi":1602.0,"kurataku":531.86,"Ren112358":616.09,"esio_trot":566.09,"takiteke":554.0,"shink0120":1009.07,"grun1396":895.59,"asagi0909":809.15,"Tsubotan":459.21,"jamilneet":838.01,"nigrum":455.21,"poxoq":1318.96,"bob07":568.73,"suesue":361.47,"michiharujp":411.95,"yuki0130":192.06,"snowlt23":749.81,"phykmqqq":1069.66,"aytr12345":149.89,"chocobo":657.16,"mtst1":544.0,"YukiDaruma":1275.64,"kuroneko398":1030.94,"n4cl":752.35,"poketorena":675.74,"homesentinel":807.0,"tunehira":867.79,"stickman":756.26,"satoyamada":857.0,"lxsdwlhh":-110.0,"akymyk":613.44,"matsuki1045":327.43,"DoubleZ":557.0,"Roy":703.49,"OsamaAlkhodairy":787.0,"london":-21.59,"parikkus":593.82,"kokubun0293":620.53,"naoki_cpp":539.56,"snpc94":368.41,"sherlockholmes48":664.41,"lofu_imgkr":893.2,"LRJ1366401054":371.53,"FizZ":1006.05,"Lithium":890.34,"Maple_Landscape":550.05,"tsupi":499.0,"sanma02":735.0,"TSSN":147.0,"xdd2016011187":116.0,"RedCircle":849.0,"yanwei123":279.51,"koo32768":537.35,"s_naoya":614.0,"zwu2016011052":585.03,"You53":1228.57,"escape173":619.93,"KUMAWO":417.85,"Zayed1":430.0,"pulsar":669.63,"yamasa":-273.0,"h4hajime":610.58,"wakuwinmail":836.62,"monkukui":104.23,"texico":546.98,"skjmp":861.62,"ZHR2017":747.24,"vih3BP":742.99,"never9612":388.81,"thedekopin0108":618.27,"shadow17":424.74,"quantu_zo":1004.5,"Yule10s":395.08,"stunfisk":87.07,"ckeshavabs":986.0,"yakoazz":1139.21,"hatto":454.0,"aseem_cu":879.3,"monir769":86.0,"clk":340.72,"monariz":771.28,"elebrain":716.27,"yttk":704.0,"pup10":452.02,"Md_Shohel_Rana":151.96,"yuu_4415":387.91,"Sher":274.27,"jiangzanzan111":306.68,"CrazySnail":254.47,"sajol":-156.0,"retatti":484.3,"nakabonne":577.79,"cxs":531.84,"kiricreamcheese":555.18,"sink":-134.26,"MegumiKato":-86.0,"st_rozeo":1016.0,"kage":305.68,"k0101":269.0,"kobaryo222":537.79,"Aogiri_m2d":410.0,"zwu2016011182":66.74,"karu":560.11,"ksomemo":639.97,"efh144":712.16,"edenth02":58.74,"zjwl2016011304":256.0,"nnmizuki":783.27,"gozenjuji":188.9,"reitetsu":758.14,"littlegirl112":358.02,"Albatross":488.86,"greenapple03":75.21,"eliza0x":616.05,"asad_IT":321.42,"iwakiriK":671.13,"tangent":583.37,"akurorein":796.52,"rinzu":1146.29,"totoro25":190.09,"leno3s":237.0,"tenkyu":178.45,"takusann":436.0,"FVRChan":561.0,"dami000":939.94,"ganariya2525":557.0,"rsy3244":798.35,"chenxiaowei":666.0,"seed_pgc":393.49,"wander_a_street":262.92,"kuma13":58.47,"afukunaga":512.0,"milky":521.54,"birdway":459.45,"Osa_Pyon":1077.0,"jack":897.57,"marupann":901.14,"wakimiko":462.62,"abc10946":627.31,"wsy127827":204.0,"lakai":492.44,"muatotto":457.0,"tonaiaki":348.37,"kirsche210":829.67,"vbird":314.21,"gobou0516":82.0,"rohanbalot":1019.61,"traveler18":406.05,"zef0":224.16,"umison":899.03,"onetow":185.0,"mp0liiu":677.24,"complement":-223.5,"SE2710rip009":1115.84,"sp4847":520.31,"rejwan":449.19,"akitani":229.89,"yasuhiroki":1011.12,"fukui_ken":285.93,"dixinkai":-337.0,"ksd777":436.21,"hideh_1231":-216.53,"yuichin925":383.46,"reihiguchi":299.4,"choco14t":438.45,"xlight789":582.42,"zuvizudar_2":915.0,"unirita17":892.33,"young1125":1123.66,"GT0803":237.0,"ykm11":396.92,"Zyouaku":402.13,"m1k__":927.56,"raphiel":-543.0,"tadak0v0":35.38,"Korinyukkuri":-71.13,"arika":491.0,"sunweimin":770.82,"Theresia":120.79,"takumi0511":-115.86,"eStar":1038.0,"hiroyuking":436.14,"moon777":280.0,"yunao":891.64,"mamime19":368.0,"shuymn":-114.0,"pandachan":226.16,"tai_spyair":477.32,"ktguy":-28.0,"kjtm0513":1123.63,"La_teth":487.6,"kasu_miko":809.07,"mebuki":-199.0,"rx5375":-261.66,"wooltea":400.48,"pit611kepo3054":81.81,"knac":-543.0,"foafoa":616.0,"sonsan":-156.74,"tofumaster":-7.0,"ayush933":480.0,"Rotari_Andrian":288.0,"kouta1612":188.04,"u_chi_ha_ra_":754.59,"chiwawa_star":573.32,"jun8d":934.34,"laomi":852.65,"kisho9730":312.0,"espartacus":727.67,"ochiba0254":669.05,"quochuya":2088.84,"RejudgeXXX":1067.0,"Ninjo":667.26,"en30":1146.95,"over110":620.08,"i_love_ayrawhsia":1660.42,"mahfuz":769.0,"towoamari":726.26,"NewbieSan":1376.0,"mutsuro_626":30.0,"arundeepak":522.3,"Joker":322.0,"todo_tt":754.47,"tockn":740.42,"tkyobc":1089.0,"OneDay":729.0,"hsoccer":874.44,"rose_gold":806.0,"giaosudauto":1246.0,"Kate":315.0,"ururu76":-543.0,"tokito725":414.0,"LittlePea":775.42,"mikan765":394.0,"E6ther":999.67,"intgrllllllllll":333.5,"YYPS":-31.0,"Sakuradadadash":518.0,"rrk":1168.37,"xiaodidi":379.44,"sidratul_tutul":436.0,"lolzano":1018.94,"caprest1":617.33,"naoyk1212":1136.05,"hippopmonkey":593.57,"prantacse14":323.41,"Kiikurage":1298.57,"material":1171.3,"Weinput":1624.0,"sharifulalam":549.0,"JackYong":259.01,"redsloop":973.16,"shopetan":661.26,"FireKing":1304.0,"mos_oknct":176.21,"miltonbhowmick":629.44,"fall":659.04,"tderkkwii":436.0,"ksohan":1122.33,"al1ce_":453.84,"ktakata":-417.0,"CKreppein":1436.0,"Eminem1147":1038.0,"shin_python":472.0,"heroccc5":127.61,"Tes_peach":1373.0,"mossuru777":534.47,"s5412039":775.0,"konchyts_v":949.0,"Shuvro":936.0,"takuya1926":138.09,"ama0219":335.0,"ashwaninsit":1304.16,"manhlenanh":1420.0,"gaurav7830":1055.0,"hano_awl":499.42,"shu_":704.0,"tiemtopro":1728.0,"Ping":402.0,"drone1973":1165.99,"assessment":2057.0,"donny070":708.96,"qinruifeng":672.41,"thoughtfultown":245.58,"hnust_DengJunjie":459.0,"tswdfop157":1614.0,"hamusita":527.0,"Fake_Death":823.0,"y_tsune":991.23,"Piyas":-520.0,"oemon":904.44,"zenito9970":1027.94,"deeepyadav442":693.07}