{"mamekin":2389.9,"yukarinoki":1255.78,"severrabaen":398.48,"zhanyl":1600.0,"daisuke44da":-219.0,"akat":2093.74,"heian":1145.06,"yhomma46":1397.61,"titia":1684.26,"season":767.66,"kobayanke":1600.0,"fshuto":987.37,"yayoi":1366.63,"zunda1st":1569.77,"laft":1065.47,"autouke":1317.57,"Hagtaril":1054.0,"okaryo":551.94,"seishun_doala":1256.95,"blue0620":1482.99,"tomesuke":1600.0,"kazuma":2428.44,"chika_haru":1001.94,"MatsuTaku":1239.3,"hanoikute5":2280.47,"Mast3110":1600.0,"ttyskg":1600.0,"kz_0420":713.37,"yijan":1600.0,"shimohiroaki":689.05,"Fxy8810":1600.0,"miggy713":1600.0,"neterukun":976.93,"amankh99":1418.89,"c7c7":1743.69,"akusyounin":1653.78,"shirobrak":602.94,"aryanc403":1600.0,"yataka":363.74,"wheson":1210.9,"kou65536":1527.66,"tonio7":469.0,"rhincodon66":1143.83,"suikameron":1279.25,"kotamanegi":2162.28,"ytsuda":1057.14,"hiroaki0615":1116.08,"fio":603.94,"sano1":1600.0,"d2verb":1194.74,"harumanachika":159.16,"takasu_tt":744.84,"ktakita1011":113.0,"JooDdae":1422.0,"developmaso":333.5,"TakoKurage":1129.41,"ff_kt":744.74,"hitonanode":2486.44,"sda0807":1600.0,"sslzzby":516.0,"wucstdio":1896.47,"mttkd399":1600.0,"nagakubo117":773.52,"face4":1553.37,"newbiedmy":3430.32,"oiuytr":-62.71,"hilltopper":1600.0,"superyusuke":1600.0,"Lower_Rating":1590.0,"goodknows":94.0,"tatsu":699.44,"RmO":305.99,"Dophin":505.44,"aisinn2":1600.0,"sam29":1600.0,"creep04":1784.43,"keymoon":1717.25,"Aparichit":1600.0,"tamurin":650.52,"sabirali2560":1600.0,"maguroguma":1138.03,"yydoco":1256.08,"rahuldugar":2014.36,"Walking400GB":507.44,"kinosyousei":1600.0,"amanesan":914.37,"espr1t":2379.88,"alexara":821.33,"yuizumi":1408.52,"waicanth07":1607.53,"ngs_436":811.78,"Tlapesium":1164.6,"koikotya":1769.98,"alicek17":1300.91,"minato774":1600.0,"sekiye":1980.42,"segorov":2119.75,"sbite":1409.94,"ococonomy1":520.58,"stk1":1600.0,"access27":685.23,"Oland":1162.91,"Daiki_Yamada0516":589.04,"MiraiNIKI":1061.11,"kyoshitomi":422.84,"gasugesu":945.15,"arpit040199":1287.12,"hirakumo":778.98,"youjik11":1332.85,"cly_gone":2420.93,"jacksun":1600.0,"RYOTA12121":1600.0,"YSakoda0605":1600.0,"cympfh":1527.89,"qrrakakh":1171.3,"daisuke112024":1600.0,"ftatsuya":1600.0,"nesya":1479.43,"wednedsday0814":1600.0,"KokiYmgch":816.59,"k8ta":1600.0,"kousy":1600.0,"kubi":1600.0,"MATSUMAT":1201.86,"okita_kamegoro":11.95,"sojisan":1087.33,"alextxu":1455.53,"ryota717":1154.79,"rentororo":-134.11,"MyNamesAdi":285.0,"lofu_imgkr":1116.47,"Motsu_xe":1400.16,"dama_math":1817.83,"grmtd087":1600.0,"muatotto":921.92,"maruny7":972.4,"tellurium":963.84,"Kitaasaka46":576.78,"downmelt913":1600.0,"ooonnnooo":1600.0,"mamao":525.0,"hidollara":1384.51,"elf48":-70.03,"Bobyama":1516.82,"yutote":1081.52,"smadarasmi":1600.0,"ritwikshanker":598.18,"Szarny":1298.14,"doradorasuki":1091.86,"Signal":584.9,"croonalullaby":1158.12,"saku630":1273.15,"NASU41":1864.55,"wakuwinmail":1277.73,"Lapinpon":1448.08,"ceni1055":1264.75,"bpine":1187.4,"xenon_chem":607.87,"oysuake":768.52,"pumpkinpietea":591.25,"koujiya201712":1600.0,"suzyz":1479.38,"hkawaguc":99.0,"weaboo":699.84,"basasi":206.41,"ast210":1569.29,"burst_000":700.05,"michael98liu":1600.0,"kentaro0407":-154.0,"sebach":1479.88,"hamuhei4869":1244.38,"fabiosalvagno":1600.0,"EOi":933.98,"attack":1253.41,"viSkey":1176.61,"nigus":2381.74,"ferin_tech":1856.09,"TAISA_":1734.01,"tada72":347.63,"hz_yue":1600.0,"hotpepsi":1650.42,"tenk9":1600.0,"QuartZ_Z":1764.3,"bored_funuke":320.73,"ose20":993.76,"kkva":617.98,"tatsumack":1488.01,"SugarDragon5":1736.93,"akizora":465.48,"yudegaki":634.01,"urp":-16.21,"azerty":1600.0,"TongXin":484.0,"Ryo2016":1664.65,"ajcxsu":1199.53,"iet461":1124.36,"proconlife":956.87,"takebozu":1600.0,"zzuli0yingyingy":1600.0,"Dishant_18":1234.99,"tobiuo1990":1041.49,"yumecha1552":1600.0,"qq1966193215":1600.0,"taskooh":1600.0,"MaC":1600.0,"Journey_begins":765.0,"yamadaaa":1600.0,"shiumai1740":-67.62,"yn0014":705.67,"williamtellor":469.05,"czsnb":1666.18,"mst1974":1600.0,"ss531122":1600.0,"tsuzuki0083":1600.0,"cocococoa":1932.48,"EntropyIncreaser":2662.0,"besood":1600.0,"tatiuo":1600.0,"EctoPlasma":1966.96,"yamamayumi9489":707.72,"emthrm":1458.92,"ksfather":682.46,"yoshimethod":1600.0,"cyka":1075.64,"threecourse":1953.99,"shakayami":1655.48,"clientver2":1600.0,"xelmeph":1388.62,"rookzeno":1611.66,"wa_job":1805.53,"kidatti":1600.0,"takagiko":1083.0,"az975310":742.43,"Genith":1600.0,"tyahan3278":749.67,"suk1yak1":704.74,"maesora":1591.96,"AboveTheHorizon":768.32,"reverd":1073.44,"zero5970":1409.3,"koujin":182.0,"sarthak1220":1600.0,"drafear":2466.05,"miz65535":1858.42,"kezawa":817.02,"kafuhamada":781.17,"Bwambocos":1613.53,"yuji9511":1410.45,"yotuha":454.85,"andooown":1107.87,"k_6101":727.21,"nikugasuki":1600.0,"tanzaku":2324.49,"sifi_border":1311.26,"zhongzh13":1440.05,"yoelpro":1600.0,"binarycopycode":1600.0,"shimizuryo":1600.0,"rantd":2084.86,"VTR":1388.4,"masaki0506":1600.0,"hillacken":1600.0,"Aotsuki_":1197.9,"Fandavale":1600.0,"hirosaji":1600.0,"i0h1n":1600.0,"hsmt":670.0,"ravie403":1073.41,"hfctf0210":1950.27,"sansen":1824.57,"miku":1501.69,"leaf_chage":555.12,"soshun":1668.51,"Fu_L":1269.63,"Ente":1205.72,"umisan":1209.68,"martha":1058.08,"dango0218":1600.0,"wujiani":214.0,"iwachanOrigin":49.09,"pittyi2nd":108.14,"amoo_safar":2175.33,"ossan_engineer":1600.0,"ryoyama":1600.0,"SetoKosuke":-167.0,"yurahuna":1849.79,"paulzrm":1165.66,"sanadayukimura73":384.84,"WBCJ12":-247.84,"iry":1246.91,"hnakashima":1041.77,"Ueki":644.91,"yokohama_jh":1600.0,"kazuyaikoma":1600.0,"hoadv":1600.0,"kvin_do_it":90.16,"tacoyama":631.71,"atsu_c":1209.8,"higashi":424.79,"King_01":1600.0,"atsushi015":868.93,"yassin":1815.25,"ith":-309.43,"ere4":813.81,"jhhope1":1600.0,"Anju_Inami":1600.0,"hitstales":1600.0,"hitman623":2153.44,"izumo":1476.27,"keiichies":1600.0,"caffeine40mg":656.68,"archit4077sh":1289.05,"suiyuan2009":2166.54,"TOBO":1264.3,"stretchybox":1372.23,"hiroa":854.06,"daibanez":1600.0,"sekiya9311":1590.23,"piniky":1205.98,"jhlfrfufyfn":1150.0,"buko":2042.37,"taxi1729":802.79,"takahashima":1600.0,"sazerterus25":1422.65,"TianXie":2338.01,"PGill":1461.16,"Huah":1053.81,"hh13579":182.0,"hiromu0601":1600.0,"Shinjirow":1361.25,"sayanaka":1600.0,"octo":481.4,"urax":1600.0,"ryutaro":1600.0,"kjnh10":1474.78,"oka_no":851.23,"Risen":1352.05,"hiddentexture":1348.8,"rumoisen":341.06,"yugaku18":1600.0,"weakestfuji":1600.0,"nadchu":1450.54,"hnkz_hnkz":245.0,"kcvlex":1744.83,"shibly":1226.93,"HydrogenFluoride":1177.95,"yankai04":1600.0,"satashun":2604.52,"goto":2646.98,"tkntkn":1276.4,"sheyasutaka":2291.88,"lwl2006":541.29,"Kuri174":898.77,"Maitneel":488.38,"MotoAtcoder":1067.34,"artoy21":525.0,"cmamt":1600.0,"kuburow":1107.37,"infer496":753.26,"torip":1600.0,"AllureLove":1020.25,"shinjisu":470.97,"mengbierr":1997.93,"Kariya":540.3,"firial02":1600.0,"polyomino":1924.34,"Ahsoukai":910.2,"Xcal":1600.0,"hironori":-71.0,"camellia26":53.84,"nullcline":1392.63,"cinnamoroll":1605.7,"shacklebolt":1165.04,"keri":1600.0,"vdg":1600.0,"erbowl":1193.23,"cherrypi59":1377.59,"heraklos26":686.96,"cowkami":458.29,"Hardoo_ght":-144.16,"keisssss":1600.0,"lambdasawa":1083.35,"akibo567":416.86,"Derek":1085.86,"mark1010":158.17,"Christopher_Yan":975.13,"asprova_test1":1600.0,"sprintertorueno":1600.0,"you070707":1489.98,"Shikugawa":626.96,"faraday":762.13,"K_Ysz":758.25,"kobyn":115.33,"Lyohei0806":1600.0,"platypus":2316.43,"AreTrash":1509.55,"ksi":1223.92,"fuppy0716":2061.7,"djq_cpp":2466.51,"xuzijian629":1660.44,"Tweetuzki":2213.3,"eddysboy":546.68,"holeguma":1858.49,"chenhoujin":1654.44,"egg_plant":724.26,"eigenvalue":1600.0,"betrue12":2136.88,"nadeshino":1147.11,"mswn7":216.0,"noma0722":188.11,"YutoCT":91.39,"wakanapo":1117.7,"toppo_mount":1600.0,"atmhusky":20.36,"AyaTaka_chemi":1242.64,"xuelei":1471.89,"usr":1600.0,"sh_mug":1600.0,"amylase":2374.65,"rehouse":1600.0,"SoutaTanaka":534.21,"yotapoon":530.75,"g16939se":1600.0,"fel1x":1600.0,"aquaCpp":1472.66,"jameshuang":703.36,"jinaybjain":1336.99,"iwaiwaiwa":610.9,"scnucjh":1180.63,"mice":1037.61,"nkhrlab":1321.48,"lxy945":36.09,"blackfish":992.34,"keroru":305.06,"gamelove765":2079.35,"unsre":1653.45,"okumura":1584.42,"Vikash1198":1600.0,"MasakiAOTA":755.66,"nulidangxueshen":647.65,"chizuchizu":710.99,"kazuno":489.11,"rareone0602":1746.86,"Thistle":1710.6,"horihorihori":1600.0,"Hiroyoshi":1600.0,"MeanyK":1600.0,"recyclebin":1600.0,"nisshimo":708.26,"pikari0904":1332.53,"ikedayuu":859.98,"lahlah":1106.0,"kagisi":198.82,"msbyama":1600.0,"smiken":2374.68,"azennto":194.44,"Shota_0214":1081.04,"sheerandai":525.77,"m_tsubasa":1536.34,"syunsuke":1154.57,"damin":534.1,"yasai03":1213.36,"saq":1600.0,"onitakenoko":370.87,"svanO":1150.93,"dnaka":601.61,"bakugaman":1600.0,"nebukuro09":2151.27,"physics0523":2047.57,"FlutCla":840.0,"tulip555":1600.0,"x20":1683.2,"keib":1083.67,"Digaus":1070.43,"rinrinrin2002":1600.0,"enookckor":1276.41,"ryota51":1600.0,"nidhim":200.37,"n_chiba_":1012.26,"sumitacchan":2086.36,"shi":1329.22,"taq225":1093.58,"kyoshi":324.98,"ktn9":418.47,"Kolcon":128.04,"SorahISA":537.68,"UminchuR":1831.15,"kambarakun":1140.17,"yamada0985":996.0,"vlado":1911.0,"ak11":1600.0,"youluoy":1204.24,"KeiichiAKIYAMA":331.05,"boutarou":669.78,"bro_c_code":1600.0,"NocturneBflat123":1600.0,"engine_moth":791.27,"kouki0826":45.0,"clock_v":620.21,"marie":1600.0,"redultimate":1130.43,"tack":147.84,"cvonder":1600.17,"muditgupta":655.77,"toshinari":884.1,"hachi88":905.32,"Casta46":881.51,"kensuken":1600.0,"ihlbbfbtr":1252.78,"zzar":1211.82,"KidoChie":1298.29,"hope_ton94":1128.25,"Minalin79":-276.0,"piketa":433.0,"YantraSarvaswa":1600.0,"jasy":1531.64,"potetisensei":2303.69,"shel":1090.19,"deoxy":1972.32,"nayuta":802.01,"IHa":1442.64,"X2357":39.47,"abst":736.0,"shiroyama":1600.0,"yusuke1990":1600.0,"gheorghe":1600.0,"mds_boy":1570.54,"diamond_duke":2777.12,"Lafolia":1034.51,"koharite":735.66,"nimon":1399.73,"makiha272":1169.71,"hirotomo":509.0,"utsumi":1299.28,"whitefox":1022.79,"gohanha3ma":226.0,"fumofumo":1600.0,"FlyWhite":1600.0,"kyo1":938.04,"islandshinji":830.17,"drogskol":1383.46,"ha_ta2":1600.0,"cyc":1600.0,"autumn_eel":1931.5,"nbcbc":296.29,"madhur4127":995.86,"juppy":1325.07,"mokrai":728.1,"nuko274":1129.91,"cotton100pc":1332.53,"ikehiro1225":725.6,"winter2121":1837.52,"aokakes":152.23,"muscat":219.24,"tamachan":1600.0,"bbpink":1600.0,"satoPPP":549.39,"tutuz":1195.09,"kusomushi":1511.87,"chocorusk":2079.26,"anonamename":1600.0,"KAZUMUSI":163.92,"suomi_s":570.01,"apigoflily":819.91,"nagasakisueo":1600.0,"syu":665.0,"daiki000":1600.0,"harryhqg":1091.55,"yuyaterada":217.95,"kichie":1600.0,"Mackyson":909.92,"backup_noob":1440.15,"reach_negative":779.9,"Almond":1377.58,"wyasuda":1600.0,"awa7449":1600.0,"TASSAN":1601.12,"Dmaxiya":1713.8,"gwsh":664.8,"adkb":1854.0,"toof":1115.29,"Kuromaru":316.96,"alphagocc":874.12,"ryoissy":2380.05,"kanzume":1234.5,"shinbunbun":-399.0,"Faisal_Al_Mamun":353.71,"HBonsai":793.5,"efk2lxg0bv4cs6gf":389.52,"shikumin":1600.0,"mencotton":1396.56,"maple116":1290.22,"hanon":15.26,"gojira_ku":1584.29,"mensan_fukuhara":1489.39,"pseudo561":1071.13,"tokachi23":496.37,"k0bayash1":-103.04,"kaage":1387.3,"colldisSavior":1632.54,"at_at":1600.0,"wshunn":1221.07,"kozima":1851.15,"ymnk_kun":-92.11,"Nanigasi_san":772.71,"hideakioi":1600.0,"sumou1011":-143.0,"coro65536":1556.93,"fridayfang":1600.0,"sakaki_tohru":656.23,"tut_tut":1011.99,"BPM390":1221.0,"Takeru_56":469.0,"ako55":1600.0,"ttlg":1187.0,"helloerasedworld":600.54,"kento_kun":1600.0,"e1352127":657.73,"kaoru1012":26.71,"Shuzaei":1340.13,"metalpelican":1600.0,"serisho911":848.11,"k2609":362.16,"oneky":653.8,"ductrungjp":1600.0,"AT274":1299.45,"Jazcarretao":178.1,"kohei7":1023.15,"radiator":369.61,"tabr":1214.63,"s0919":528.0,"s5412039":744.1,"nps":1144.93,"okkuu":1414.11,"bigcat":2050.66,"yatuba":1330.27,"kamina_zzz":1600.0,"pdwd":658.29,"nekoTheShadow":1188.98,"souanz":1138.21,"nekonekoneoko":888.32,"kamikazu":1600.0,"nnsr":1600.0,"monk78":1600.0,"kada_1998":1534.03,"Atalasion":1373.0,"ynymxiaolongbao":2232.68,"peroon":1237.41,"atsushiushioda":1600.0,"buzzbuzzo":749.63,"atzou":-152.21,"koji022":-692.11,"KoffeeKoin":917.13,"oneplueone":2719.0,"toshikish":258.0,"Hec":2318.72,"oshibori":1442.09,"penn":-404.21,"remin":1763.77,"noikari":384.78,"asoasoaso":906.21,"tusaitoh":1600.0,"takoshi":1907.5,"horiuchi":1600.0,"agw02010":911.76,"rickytheta":2741.89,"WrongAnswer":281.81,"nanae":1726.06,"hrOarr":1098.83,"somq14":1994.92,"shibh308":1799.22,"Kats":1346.88,"togatoga":1632.42,"fine":1882.13,"ugnom1121":1237.08,"bigdamp":1600.0,"tyclear":617.53,"LLI_E_P_JI_O_K":2124.5,"foreverlasting":1347.29,"math":2625.5,"tamanugi":1600.0,"Cerberus97":2369.6,"abuCma":-126.03,"hig98ingro":1320.06,"yosiokade":1600.0,"T4":1600.0,"Nekoroko":496.15,"keigomori2001":57.34,"Zz7":1224.12,"tsuyo":1600.0,"fxt":1094.92,"hiramekun1995":976.25,"shake":1585.36,"chb1975":2153.66,"takaya":795.29,"iehn":2180.85,"piro77":576.97,"yasu123":1600.0,"zaki_":1812.83,"only_hard":2913.18,"tmkshm0217":1245.23,"procedure":1600.0,"hirokazu1020":1770.66,"nomi":1193.21,"eita0368546":621.84,"onoken5715":1600.0,"Johniel":1531.28,"yuya178":1655.17,"kongroo":1830.03,"White_Green":1600.0,"chantchanakya47":1600.0,"to12lz":1125.85,"akio77":1600.0,"mathlegosuke":1640.1,"dbftdiyoeywga":468.85,"BSer":825.74,"grayf":1159.71,"pandora":1600.0,"aim_cpo":1261.46,"udonko0516":1185.63,"taitan0655":-487.0,"Ahoxa":806.76,"tkdaki":1600.0,"Komaki":2657.12,"aakyara2008":19.56,"Hirokazu12":927.13,"TadijaSebez":2458.64,"GoldIngot":1600.0,"the0troop":1600.0,"lakshay_nasa":1600.0,"sugarrr":1903.89,"ultmaster":1960.61,"nsano":1600.0,"tomowarkar":444.38,"flirtguru":1600.0,"chiruno":511.0,"haruhiko28":-133.0,"makishimutomato":281.19,"b2563125":1736.25,"xwd456":-66.16,"ukikagi":2080.54,"spica314":1930.88,"Swrrt_11":2282.0,"savacska":2121.9,"kenichi0117":1600.0,"take60328":995.0,"Lee2004":463.17,"march62":1600.0,"too_lazy_to_code":736.0,"Rakaz":1600.0,"Yoko453":1034.13,"kwfumou1242":1447.33,"rodea_0952":1331.56,"takus4649":840.78,"hakoshie":907.97,"Regent_50m":1000.93,"jaripan2":947.18,"Sometimes731":876.5,"foobarhogefuga":336.69,"Equaver":-98.95,"yamanaka":1600.0,"hamko":1812.65,"iwashi31":2151.79,"TSSN":415.17,"convexineq":1639.42,"sakana27071":473.47,"iakasT":1589.23,"horinoayame":1496.15,"leaf1415":2086.0,"university":1077.71,"mitsuba":278.65,"springroll":985.01,"vibage":1086.68,"hoshi524":1721.52,"leafmoon":1894.72,"wata":3128.0,"menphim":1337.87,"ren1212":1600.0,"daihuku":648.26,"almichest":900.91,"Eric1028":966.33,"yokoyan":1600.0,"shinji":539.26,"nenuon":1589.13,"reud":705.51,"ogy":690.06,"cleantted":1245.08,"mochiii":1108.31,"akswnd98":1600.0,"xecua":915.51,"kawazu":1203.44,"AlanWaP":1502.57,"kakira":1617.96,"z0010":1600.0,"ninja7":1839.98,"takas":1600.0,"seastar":1600.0,"mymyyy":434.0,"mmc":1600.0,"saku_uma":1600.0,"YamadaAkira":1600.0,"chuka231":1152.16,"risujiroh":2205.93,"kamojiro":1436.64,"JamesYuki":1600.0,"melon":1600.0,"klno":671.31,"ManekiNeko":229.11,"walkre":1686.45,"srfy":661.47,"slime":746.94,"Allen1223":897.42,"kkr":437.09,"bear0131":1127.3,"pachicobue":1938.56,"ikatakos":1810.11,"takky1111jp":1600.0,"suncongbo":1332.96,"Misteer":2045.77,"Abukhadijah":728.24,"yamunaku":1731.61,"DarkYoshi":1070.64,"xoke":1319.35,"algon":1741.25,"valuna":1917.91,"jibanchan":536.17,"fickleness":444.8,"katata":550.28,"sumoooru":1932.46,"June_boy":2068.04,"Okay":1239.22,"ita":773.0,"ysys13":626.93,"onesbasket":1600.0,"TKR18":1012.6,"yoshioka824":1600.0,"FelixChen":1642.1,"Diuven":1884.13,"wans":-92.0,"TanakaTaroh":1442.35,"totototakemu":802.69,"akimotty":798.97,"alte":921.0,"keep_OC":1234.01,"tarattata":1353.66,"tk72HS":1151.08,"sgtukk0128":1084.57,"enjapma":1858.85,"rmurata":1600.0,"YK0809":960.02,"takeru0913":1600.0,"naru1":-12.12,"Alpaca_666":-108.0,"onjo0127":1805.92,"pynomi":940.35,"yamakasa":1070.2,"Phoenix3718":417.81,"e0908iked":1284.66,"T0726596":1600.0,"anhtv":1600.0,"dat160601":1130.32,"r_y_89":1600.0,"Xere_yukky":-725.0,"naoyuki0428":1600.0,"amaotone":1438.87,"dalex":1928.6,"taiyooooooooooo":336.15,"kxc01141":379.05,"chouxcreams":1600.0,"ynq1242":1946.96,"seiritsu":237.16,"chore":1600.0,"takamoto":2227.25,"suwakotaro":1323.11,"anmichi":1216.91,"zkx06111":2171.85,"tomo_f01":600.88,"KenK":1600.0,"Murray":1600.0,"futty":1070.59,"kaito72":-73.31,"peradfn1126":1839.2,"miyajiro":1814.22,"HBK_Wasi":871.77,"kussy_tessy":364.16,"goodbaton":2446.12,"momotaro1303":539.33,"TangentDay":2635.01,"zengzk":758.38,"miyamoto_aiueo":258.0,"n_dao107":1925.44,"arseny30":1600.0,"BONANZA":1600.0,"beet":2505.02,"RRFKEISUKE":959.07,"Tommy6":1101.0,"xlxkazuki":733.0,"fooractal":1902.91,"atcorder_eustia":1081.5,"xcao":1072.28,"Keno42":1600.0,"Ashishgup":2057.16,"saba":1158.74,"licht0":86.95,"felix925":-272.0,"kanetest":1600.0,"darkkcyan":1791.87,"firkirb":1435.68,"olphe":2328.21,"lfforu":1841.0,"st2d":1600.0,"furachai":1600.0,"mo3tthi":1060.78,"akiha123":1600.0,"matsuo":-58.99,"uramnar":1184.1,"hide0903":480.95,"Neroldy":914.82,"supy":2600.85,"tspcx":1993.47,"macaroni":1320.62,"Okome17":1600.0,"naranhuu":1249.05,"zhaoqc":1600.0,"peace_of_junk":1041.49,"Xifon":1600.0,"kaz72x":1841.82,"toame":1497.13,"MiuraMiuMiu":1346.14,"potter1024":1600.0,"killerrk":493.08,"hogeandfuga":1056.78,"hagebooi":1695.46,"darushino":623.71,"horipy246":1600.0,"arcwatercash":1101.0,"sabretooth":1600.0,"motohacy":1600.0,"ei13333":2249.36,"riantkb":2521.44,"kshinya":1884.5,"ate":421.31,"Jun12":1015.28,"kyopro_friends":2020.02,"tarao1006":1600.0,"Corvvs":1779.56,"MAK_culcul":2521.71,"solver31":1600.0,"taka_katsu0411":-110.0,"ishikado":1739.18,"wanghaoze":313.81,"Shawki":503.07,"PIandS":2530.12,"Hewla":1535.44,"mdj982":1858.29,"shado_w":1772.0,"keihigu":1600.0,"lzw4896s":2102.04,"semantyc":724.42,"kohdai":737.29,"Mayimg":957.2,"yui_nan":106.34,"basuki":910.75,"oevl":910.52,"cn449":623.26,"loremua":995.29,"Kmcode":2519.7,"masafumi":1505.86,"Kenkoro":691.97,"kobataku":1600.0,"monman53":1674.42,"yukirin":1104.49,"biltharesatyendr":1105.41,"nikkikei":415.85,"mura5726":465.69,"silly_1_2_3":732.0,"nuhunune":653.58,"vikas_nitd":1600.0,"midoriiro":1600.0,"hogeover30":1480.96,"misosoup":1488.62,"miy":1600.0,"yosqlo":46.01,"everGreen":1600.0,"tr2azb":1600.0,"Maydaytyh":870.37,"keitarou":-122.71,"Origenes":1851.93,"zero_":1600.0,"totori_nyaa":564.84,"ijm":1427.96,"mofmofharuka":476.89,"arrowsz":1600.0,"tm28":1600.0,"Yasuo0521":1600.0,"aabcxabf":1600.0,"namamono02":1600.0,"ebina":-20.26,"jell":1785.27,"Jiangkp":1903.58,"akariki":1185.08,"Kandam":169.0,"Ktya_59":1848.29,"swkfn":978.96,"m_buyoh":1790.94,"okd":1600.0,"tossy":2206.05,"OZY123":2038.52,"xiaohejun":885.7,"ginzi":-725.0,"fshin":1600.0,"MMNMM":1952.37,"fal_rnd":1587.63,"x0214sh7":1420.83,"mh755628":1448.91,"okitz":1022.45,"satanic0258":2391.66,"wtl666wtl":1938.36,"wakax365":1778.21,"Clarinet":1600.0,"madako":1600.0,"daikiOka":874.73,"robonchu":-124.0,"mino":1673.59,"palpal":1611.05,"asdf1":1369.15,"GNX2":1600.0,"indivisuals":1205.46,"montyaxn":1600.0,"hironiwasm":1600.0,"cyclatp3":1163.57,"Meple":2103.98,"HSC57":495.0,"AKRAM1871":1600.0,"masato125":1600.0,"omega3":1600.0,"LeMur":2041.99,"teto":1600.0,"antong":1600.0,"kobaryo222":1307.83,"Azumayan":810.6,"rtia1227":1711.33,"klng":-468.0,"shaw":1600.0,"xlight789":1204.75,"lych_cys":3082.53,"koka":1102.07,"nekoneko":672.16,"hkrhashi":317.23,"v2n":1151.46,"kinton1116":1600.0,"soneo":1600.0,"daiwakun":1023.23,"kkiriyama":1600.0,"kimiyuki":2494.29,"hyttcnkf":1508.23,"bav999ms":1600.0,"Noge":1600.0,"aloo123":288.38,"jsOJ":964.6,"okayamen":1600.0,"Eldora":1954.25,"shadwanna":1600.0,"DongChengrong":1028.72,"nakana_kayaru":1209.64,"Ebishu0309":831.68,"yishikaw":99.0,"spider_0859":712.0,"ziroppe":783.6,"caeious":2182.51,"hai":2100.44,"dxyinme":1533.54,"ippei":1600.0,"kanekoshinn":877.2,"yukkuriesu":1463.04,"luty":1200.08,"Panda_hu":1389.43,"sewage":1134.32,"LanrTabe":1534.93,"maatakamii228":928.0,"ukohank517":1452.11,"SAIF_IIT_JU":94.0,"ZollingerPython3":1517.38,"lm5003e":1600.0,"kurage":1600.0,"gari2":-97.75,"nilesh8757":936.06,"HeavyMind":559.96,"okudeottu":1388.59,"shinike":1998.36,"Ryosuke839":2138.5,"n_knuu":1760.14,"yana87":1538.66,"STAC76":1600.0,"yaoshimax":1897.31,"Sir_Edward":693.0,"sash0":1682.87,"toshiki_full":1498.89,"orange55ship":529.21,"asuka_kurasina":912.47,"catupper":2597.72,"ChiyosBigDragon":1288.4,"yy4":1324.44,"nononakahira":1600.0,"banri":510.04,"TAB":1907.71,"sintan":929.37,"horusuto":492.58,"ikd":1455.64,"monkukui":1572.57,"nomuDog":1163.22,"mkut":2185.0,"tokoharu":2604.45,"was_n":1941.68,"noobDetected":1600.0,"nphys":1168.44,"raja1999":1698.29,"temu":202.53,"dragon_twister":1213.54,"goropikari":1158.93,"Ricky_Ban":834.5,"Halifay":1574.45,"NoukouKei":1600.0,"astro_lion":1137.25,"arzk":1596.55,"numberyo":-227.33,"ryoo14":275.0,"novemura":1514.22,"punkiel":684.31,"musaprg":763.77,"imsupercereal":2447.0,"bradypus":1600.0,"Kichi_2525yt":913.64,"fpcsong":1600.0,"a_muraka":889.1,"Sashiming":1181.91,"wisteria30":-171.45,"claw88":1818.82,"chun1182":1374.92,"IdealLife3":1136.69,"kswrabbit":1073.0,"takumi152":1675.19,"pslime":1019.79,"nirvana":1600.0,"ggggg":1275.08,"isher":-155.0,"Hoi_koro":2252.46,"fugusuki":1502.41,"zawa":1600.0,"lowjack":1362.0,"Brijesh1in":1600.0,"Katudone":1600.0,"gksato":1546.15,"kura3618":1600.0,"ka_mi":427.27,"pika53f":393.75,"leashptntl":1645.23,"kumalimak":1329.72,"moon_27":-77.0,"koyasu312":1600.0,"kyuridenamida":2150.96,"hy1004":1485.19,"fukki":1217.24,"baseballyama":896.97,"tallestorange":1256.05,"halfpennyworths":1013.34,"dameningen":1275.35,"jp3bgy":1391.82,"saxin":1600.0,"masaomiyoshidazv":1600.0,"ssdh233":1397.0,"pillow97":2055.85,"apoorv":1038.41,"Korenaga":1600.0,"rahul_":1719.0,"khigasa":1600.0,"linkct":2534.85,"msdipu12":1439.0,"hemnath_d":1143.67,"kartica":1189.23,"Autumn_A":1199.5,"hikarutakenouch":-224.32,"yosss":2339.5,"nabepyon":1600.0,"h_izu":713.54,"ichiichi":1600.0,"tpnbnk":1040.65,"dereksodo":838.16,"ichyo":2167.98,"yuusti":1969.04,"gazelle":2243.81,"leftymasa1227":1600.0,"sarthakmanna":1144.3,"nikki1126":1600.0,"code_jnv":1600.0,"SaikatS":451.11,"tak11":-468.0,"atez_r":866.89,"occhan":917.93,"mosquito_":874.0,"Tqk":1368.45,"kr":1050.54,"LeroyAnderson":1600.0,"ichgw":694.33,"stmtk":707.73,"pontaryagin":1299.4,"semimaru":1112.78,"maxime":1600.0,"tomcatowl":1790.58,"dakarabook":1600.0,"ganmodokix":1455.14,"sirkerf":-234.0,"antontrygubO_o":1830.09,"arvindr9":816.0,"ransewhale":1897.27,"YuyaPhys":1040.86,"tnyo43":1561.86,"ryo1126":1065.26,"Flourite":1600.0,"shidenvip":893.0,"musharna000":1881.41,"crom":746.35,"y2kuroda":1600.0,"yyhhenry":1575.0,"a2f3ywth":1600.0,"agw":1525.31,"t2008":1600.0,"maozhengxiang":452.84,"ashik_jiddney":601.24,"Ju_Ga_Me":1048.32,"shimon24":763.37,"idsigma":1524.59,"mgr31028":1600.0,"wappen20":1600.0,"add_bakkers":1600.0,"espressivosubito":1655.73,"irisrune":1199.11,"iva7":590.31,"pin":961.14,"suzume":1883.34,"Gloid":2153.6,"rikein12":1618.08,"Kaichan394":1600.0,"samjoe":1600.0,"heno239":2159.42,"liangsheng":1516.57,"c2masamichi":1117.08,"thedarkworld":518.94,"Maricom":1600.0,"DSMcKey":1196.84,"h0nestliar":1600.0,"morio__":1514.47,"natsumikann":492.42,"matplus":1600.0,"lolicon123":1600.0,"ganariya2525":1415.13,"DRA":1879.5,"trabbit":705.0,"pnumason":1261.63,"pulkit96":1575.32,"luma":1810.85,"You_Know_Who":806.79,"andyy143":1600.0,"huwamoko":546.62,"shion":1600.0,"plasmaeffect":1786.01,"pto8913":304.47,"jiwon0522":1999.62,"ZYCSwing":1786.43,"Akitack":1600.0,"Winniechen":2007.0,"mashpoon":537.32,"touyou":1278.11,"shell_wataru":1362.22,"xzy":1835.34,"linuxojisan009":276.37,"sazzadrume":-65.11,"urumeiwashi":1299.57,"vipmario816":1117.31,"tokkiyaa":657.0,"omarosamadiab100":1477.0,"nexdra":783.0,"hyasuda":660.0,"Home3":1600.0,"tosite_perfect":1600.0,"happyisland":-487.0,"takaaki82":1044.45,"mosesmayer":1559.43,"rutas123":870.84,"hyon":1801.21,"kyoroid":566.79,"hryshtk":673.11,"mps2000":1568.16,"skhiuk":1600.0,"cinnamon":701.72,"banboooo044":1378.65,"zekatsu":838.86,"nynnmaru":20.97,"rishii":1284.82,"baku1101":955.34,"sykwer":1393.2,"minus9d":1657.16,"Noimin":1602.3,"Tsuta_J":1986.09,"bigdekopon":1681.3,"nishionyama":1447.68,"toromaki":867.57,"vivviv2":1600.0,"kawakawayasu":1600.0,"quiver_algebra":1600.0,"mhrb":1423.04,"wh317706":747.88,"emonosuke":1334.61,"WinField95":1332.97,"kagasan":1811.89,"nai":2305.19,"Cebu":-172.58,"S00391":1600.0,"Lemon293":241.0,"roto_37":1641.05,"kim2038":429.17,"kemingsurface":1118.67,"yn1323":-764.0,"ms_ishi_00000":1600.0,"sunyryr":1600.0,"zettaittenani":813.0,"bknshn":1715.5,"victorique":1834.59,"yujidx7":1488.06,"haya_dataphoto":1600.0,"thriftRL":1600.0,"kametan0730":342.2,"ryu022394":224.0,"hamaryo":1600.0,"mutuhuhihusenonu":1359.09,"EntityIT":1180.63,"SoulTch":1866.68,"ashubeckham":967.5,"chemistrae03":739.29,"eha":2384.48,"ningenMe":1476.99,"suzukisan_love":622.21,"shyyhs":1646.14,"snow39":1528.08,"Water7mark":570.21,"dynamis724":1511.99,"hkurokawa":1353.67,"MShinokawa":651.23,"Alexandr_TS":2392.0,"aeronautic":1600.0,"jaizzB":1600.0,"kurenai3110":1779.02,"Ikok":1451.25,"Yuuki0418":-143.69,"xuziyuan":1379.49,"japanesekeigo":1244.5,"Vista_win":1600.0,"harady":963.29,"jcy16080001":-307.46,"takahiro55555":1600.0,"a2stnk":1927.94,"parsee1053":539.21,"nikkei1103":1600.0,"lrmystp":1942.37,"kenkoooo":1902.35,"anagohirame":1659.67,"cjj666":1375.26,"KonSato":687.12,"nuzpuz":769.41,"bup1028":13.75,"woody":788.87,"kyomukyomupurin":1207.53,"teafrogsf":1600.0,"ysanopp":251.56,"takaharada":1600.0,"jute":381.37,"hamayanhamayan":2270.99,"pinebooks":1232.37,"mikit":1723.44,"Suunn":1720.97,"kkyusuke":1600.0,"abab":784.46,"Zain":1670.72,"dohatsutsu":2261.42,"Gobi":1638.45,"ei1710":1217.45,"ayamu":-697.0,"nahcnuj":1050.26,"lawliet3110":1272.42,"kira924age":1042.91,"reew2n":2284.35,"Kucing":8.16,"kirbyer":1600.0,"Ziklon":1600.0,"FS1229":568.72,"MEGANEnoKAMISAMA":1091.96,"inutel":1600.0,"startcpp":2178.62,"Calico":1705.82,"starlitsky":1341.22,"Ichijyo":706.84,"awawawawa":1600.0,"flashlight":648.79,"lacitirc":2664.0,"ishigen":1600.0,"kanra824":1457.18,"creatorx":784.0,"WAAutoMaton2":1938.86,"Chanyuh":1485.07,"masu":1013.74,"stimhoo0829":336.9,"tShun":151.91,"Hirosesesese23":1381.61,"uemt1":730.68,"pocketpair":1030.22,"kilattoeruru":1289.55,"pentab_seijin":394.77,"ward1302":1539.12,"h_gnome":1600.0,"atsuya":1600.0,"neel783d":1600.0,"sei40kr":1175.33,"Mr_Treeeee":1540.33,"akht":799.97,"zuzuzou":796.4,"sk8958":1600.0,"TasmimDisha":-641.0,"skytomo":641.93,"micami":-325.0,"davidcairuz":709.44,"Pomato_b":382.31,"tonami":1600.0,"iTakashi0ddh":-339.0,"kentei":499.43,"jki14":1982.41,"badassiumoxide":649.69,"tomatine":176.0,"pyash_123":1217.04,"yswness":1441.51,"Roy_R":1467.09,"catoon":1604.45,"kekkenoke":1600.0,"tkzw_21":1629.42,"ShinjiSHIBATA":625.24,"itohdak":1241.09,"yukidaruma6":1806.91,"inoudayo":549.28,"kmatsunaga":1542.78,"yebityon":1007.2,"aajisaka":1858.05,"Sukegon":1600.0,"hikatyu1029":1600.0,"merom686":1815.56,"UPS":1074.69,"ryuki":1600.0,"tonegawa":901.2,"okura":1750.25,"tigertang":1443.92,"Laika":862.61,"Himmel":-377.9,"KEN_RP":917.21,"tanakh":2130.67,"selpo":1678.91,"kage":899.44,"tmsausa":1263.58,"nakamu":1600.0,"Yz_vica":796.0,"ting":1600.0,"kzyKT":1912.48,"rika0384":1461.79,"dilmnqvovpnmlib":740.17,"impeccableaslan":309.07,"stonekyx":1600.0,"nxteru":2164.04,"watamario":435.89,"Reideen131199":480.15,"tempura0224":2135.43,"yosshy0228":1600.0,"takashi67":1600.0,"naoya_t":1586.67,"dreamerspark":762.07,"mechanicalpenciI":2266.82,"harada":1600.0,"hayatoto":91.0,"Pellier":717.84,"Gaozou97":862.66,"fermat820":1600.0,"jyongh":597.32,"nu50218":1524.67,"aueno1986":1600.0,"n_o":1600.0,"okadatta":1600.0,"ten986":1739.36,"OvThAlmin":676.01,"bonsai878":470.21,"igara432":737.72,"kyawakyawa":1356.76,"funa_funa_panic":1449.0,"imh":1540.38,"katsumasa":1600.0,"babingbaboom":1116.85,"petrouchka":768.41,"yanhao317":1209.72,"polarbear08":1498.52,"fgwiebfaoish":1466.89,"char134217728":1875.5,"salil03":1600.0,"enomotokan":1600.0,"kakakakaneko":1517.29,"suzu6":930.0,"seema":997.18,"ahzong":1600.0,"nYJee":1600.0,"dadada":1600.0,"tRue":1005.91,"yn96":833.95,"ajinkya1p3":1748.48,"iloveUtaha":2438.54,"spihill":1437.19,"lOhln":977.0,"Rzepa":2575.35,"moro":940.05,"shise":1600.0,"Respect2D":1618.79,"lodnix":955.31,"proteasome":1122.61,"guricerin":351.69,"hoda":1600.0,"Taratara":636.37,"birdway":1555.55,"kame_2211":149.58,"NaoyaSawaguchi":1600.0,"Pyons":386.18,"lapis_Lazuri":836.77,"yosiiii":770.78,"fumiphys":1584.12,"DapaRet":855.52,"lauzm0":464.0,"KOJIDERERA":1600.0,"coco18000":1647.43,"Cossie":802.82,"Ksyun":1600.0,"hide1214":1688.53,"mine691":1102.18,"shirodoni":1674.02,"shinchan":776.5,"nyon":884.58,"makonagix":1419.27,"th90tk297":1426.87,"shin98":1600.0,"kurose_th":1111.32,"damekamo":1096.64,"fragusbot":1793.89,"prd_xxx":1599.95,"motecha1j":1600.0,"kenta2997":1455.18,"starboy_jb":1102.62,"youenn98":1600.0,"negiii":1600.0,"norezark":485.37,"ink":68.79,"firiexp":1393.64,"yumarimo":698.62,"Sano98":710.84,"amyu":729.68,"Enal":1600.0,"Raguon":594.82,"zazen":822.92,"kondounagi":122.68,"PyOn":1600.0,"kazz333":1600.0,"Mirage":1259.0,"nejineji":1878.75,"yousolo":883.2,"zundamochi_1117":1633.36,"taiyok":1600.0,"kaito2280":610.61,"YuyaOkayama":93.0,"mashinosatoshi":1107.48,"windflower":1555.18,"kenta0000":636.09,"ttttan":1436.14,"kkakiharaatcoder":1600.0,"mohanr7073":1600.0,"chocobo":1576.9,"r3901":368.23,"nerimark":1600.0,"tubo28":1793.7,"hychyc":2078.0,"ootanih":1600.0,"qdd":1600.0,"habara_k":1586.83,"horoyoisawa":1600.0,"panda0226":1600.0,"mtsd":2211.62,"waaadaaap":1600.0,"fjhr":898.49,"tanitanin":557.37,"katom":1600.0,"mechfrog88":1082.0,"daiota":1017.26,"illyasviel":2491.38,"zyc":1600.0,"yuto953":1311.16,"NOSS":1640.01,"BobyamaJonthonta":1473.01,"inazuma110":867.41,"amanuko":1651.33,"yasudomi":1600.0,"int_cl":1787.5,"nessie":974.89,"azarakko":1600.0,"tenkyu":967.77,"Mojumbo":1302.72,"yh1224":1108.76,"tatuhito0125":1868.53,"kenken714":1344.24,"ats5515":2539.97,"revolIA":1186.12,"nobleman1":1176.31,"FigFig":2311.79,"yk11":580.17,"prince":1107.7,"sciencesakura":576.0,"kort0n":2133.36,"paddy_ist":387.42,"shiboy":1211.37,"maze1230":2114.15,"kroton":1818.71,"AnnieCai":1102.09,"BIFFI":540.26,"zhongzihao":2365.0,"roiti":1724.87,"makkii":385.77,"ks96neko":162.15,"xxkiritoxx":2038.19,"ngs":1289.9,"kanjin":351.36,"kiki33":1333.78,"a524287":1634.48,"Kambe3141":1435.82,"spar5h":1636.56,"nagiss":1916.33,"grumpy_gordon":2529.44,"Aman_98":1011.47,"tube_worm":1714.18,"soukun":1600.0,"fauzdar65":1321.31,"Spartan":833.28,"Shibungi":1324.1,"angelic9":895.49,"CHENRUIJIE":584.96,"RHoman":1008.69,"mnrskym0227":750.45,"yoshnary":1602.48,"itoHO":-173.0,"njha1999":1241.33,"ringo9971":336.32,"htkb":1595.41,"ctyl":1996.62,"tebasakioisii":159.9,"toa2525":1690.97,"LayCurse":1720.66,"Yang33":1672.39,"tuko_black":-697.0,"Tendaysago":1071.28,"beobeo":1037.13,"Suibaka":1652.53,"tanukitune":593.18,"dot_haraai":165.0,"garasubo":1532.82,"private_yusuke":1109.36,"imxian":2180.01,"tancahn2380":1465.07,"qLethon":1373.26,"arjun_9426":1162.39,"Buddychen":1600.0,"daiju":1473.7,"takechan":865.37,"kurarrr":1605.4,"Yuroru":1339.05,"mzuev":2449.71,"cedretaber":1323.11,"ptt_kr":1551.37,"sarashin":816.22,"Fairuzi10":1648.27,"keidaroo":1411.08,"showoff":1158.72,"gyuuto":1437.87,"yu3mars":1616.31,"takeo1116":1621.48,"tamihuru":952.79,"uraoz":373.89,"odanny":916.21,"nk19963":1600.0,"aki167yuuki":1600.0,"MRtoma":1303.63,"ishida5588":566.23,"hs484":2019.63,"Pro_ktmr":1586.35,"samraimarket":894.93,"verb55":942.56,"abc050":2140.12,"tokumini":1762.22,"nanatoday":1177.8,"kubo_nits":1356.6,"colun":1696.53,"thirno3153":1651.34,"fmhr":1170.37,"hq8398":1600.0,"mafillth":1119.51,"HossamYehia":1106.0,"mobileOnion":617.97,"nikutto":2296.56,"Rose_max":1979.32,"khksmt1999":630.64,"moa":274.05,"oshojo":1171.54,"spawn":1835.67,"minus3theta":1727.55,"ty70":1238.5,"NapierJP":972.64,"sarwarkhan":1580.52,"arfz":1290.63,"teacup":958.19,"waione":274.0,"RyotaW":658.25,"shubhamg931":1380.11,"taiyou":1600.0,"shimaw28":729.67,"guvi007":1024.89,"LeonJoel":966.25,"base64":2190.7,"siiiii1107":956.02,"nyashiki":1335.41,"FF256grhy":1936.94,"haraduka":1724.59,"zhan8855":2462.23,"misora192":1268.79,"MicGor":2113.71,"hsl2363":1474.04,"Luzhiled":1614.48,"alorie":1037.66,"Graphcalibur":648.1,"ganda_coder":1016.85,"k1832":1600.0,"ToMmyDong":1687.98,"wwh0613":1600.0,"nii":1211.72,"taka99":1236.37,"kuroku_969":608.55,"bababamizu":261.91,"future731":1118.54,"bereke":1600.0,"MB1151":1512.83,"abasadzishvili":1600.0,"upura":1088.18,"Nishkarsh":1353.7,"hjw":1616.26,"asuma":1167.92,"ligen131":1250.33,"ppstp":1600.0,"mihai50000":1405.78,"iaz1607":1011.0,"tonnnura172":976.0,"bhayanak_atma":1600.0,"aj1m0n":1600.0,"kumamonyokamon":847.26,"nakano":2052.5,"j06052":620.38,"terafon":-57.0,"bigelephant29":2185.24,"moritaoy1128":1562.5,"masquerade0324":992.86,"masakam1":1066.62,"zhangshuo":1600.0,"jiaqing23":1510.68,"minszsz":51.0,"huangwe10":1600.0,"Dakuon":510.6,"kaisei705":494.53,"kt_tenel":1673.48,"nuwatan":1600.0,"shiba560":735.54,"fiord":1966.0,"romanasa":2241.36,"toloraia":1501.84,"baito":1370.86,"kibi62":1314.65,"Juyi":1803.5,"icacht":1046.55,"motacapla":775.0,"xb82":778.0,"patsy":1600.0,"ringokuppa":118.95,"ogingin":1707.21,"ffacs":1600.0,"WahrGrowth":1244.42,"mnao305":466.73,"Alt3":1508.95,"hasi":2147.98,"Ti11192916":1659.9,"material":923.04,"akki":365.4,"shirowa":1688.16,"Rew":907.08,"kuzumin":1088.12,"yftv6203":906.45,"Bantako":1332.34,"shompepe":366.44,"patahene":1243.73,"martini":921.64,"hori1":1600.0,"vain0":1699.52,"zhan8822":2679.53,"akarinkof":696.7,"niwa_nowa":545.17,"kawasima":1600.0,"T1610":1700.05,"nrmt":774.05,"kajyuuen":607.08,"nkoz":406.24,"minaminao":1972.98,"kotatsugame":2077.22,"etonagisa":1810.81,"uk000":630.63,"ochiba0254":1445.97,"genkinanodesu":1619.18,"f_t_ikt":1176.89,"shinobe":192.09,"murata":1438.9,"bomac1":1613.88,"YamagenSakam":1045.42,"tshirakawa":1736.44,"sada":363.32,"Vitamin":994.5,"Artoria":1575.2,"hamukichi":1263.91,"cojna":1628.99,"tranxuanbach":1930.0,"qqr_i":853.87,"task4233":1277.55,"beginend":2376.43,"shindannin":1831.63,"canon4444":610.47,"xhmjm":1600.0,"funcsr":2457.21,"hasamaku":535.23,"tanasaradu":1668.0,"tokutake":1600.0,"megamanvui":1600.0,"ikom":1420.38,"SGI":1979.29,"rachits0512":-935.0,"Paydayzcool":862.51,"shoyoku":364.36,"esio_trot":1123.79,"meooow":1989.52,"matchapy":448.0,"Paliukh":1723.17,"Nu2020":611.63,"xml9shiki":1083.1,"sntea":1769.75,"yuki255":835.65,"Gacho_0716":1721.02,"my34y":1600.0,"dm8sh":1600.0,"Tallfall":1559.84,"stdll":1741.35,"logicmachine":2519.6,"lp6m":1346.09,"jiangshibiao":2781.47,"mugenen":1619.8,"makkkki":539.17,"akun0716":625.14,"Akatsuki1910":505.44,"kuribo":503.63,"kuuso":1787.94,"tsukasa_diary":1782.68,"YutaKohno":1309.42,"skeletont":1369.18,"tetsuma":934.54,"maple":1475.84,"m0bec":1085.55,"fukubutyo":1071.26,"pei166":650.22,"digcboy":982.0,"kouki1223":2076.18,"JPnakamura":688.86,"srikkanthr":1600.0,"beatat2018":856.06,"shunsasa":1301.93,"hiro_hiro":757.55,"tida11":63.24,"moririn2528":1954.35,"uukosnubeyn":354.44,"yasu42810":1053.48,"hururu":1231.12,"pompom":46.32,"IamHIRA":1110.6,"selecao3":1600.0,"ophelia":1173.73,"yamad":2017.0,"kurakura":1354.7,"skfwMelonpan":734.0,"kt0221kk":601.6,"haodo":251.2,"khir":1588.45,"eagle_i":1215.83,"shioshiota":1599.64,"mmu":1600.0,"konjo":2052.39,"TKTKST":1600.0,"haru_44":1416.05,"Hatsujime487":734.28,"logicer":154.79,"torus711":1657.47,"oyr":780.88,"eulerdblack":1069.92,"phystak":1254.58,"makecir":1443.32,"cellphonium":377.53,"Flugan42":2009.43,"nono_fg":354.65,"mitsuo0114":1134.26,"koda_1017":524.68,"passer__":817.43,"nitumeta339":703.93,"Ryoga_0212":1513.84,"kaz1988":1491.07,"celeus":1600.0,"mi_tesseract":1581.98,"tokizo":882.17,"Riana":415.83,"scor":1467.0,"uni745e":1183.65,"AokabiC":1404.74,"deep1999":1154.0,"SuisoNoOto_":529.69,"commy":1598.66,"rikupin1105":-94.0,"riorio1174":408.0,"ecasdqina":1637.34,"elm118_C":1600.0,"genso_miku":1600.0,"gyuudonn1222":415.9,"qrlokki":1600.0,"fmp":760.17,"mnyk0822":1600.0,"cutekibry":1005.02,"chaemon":1799.74,"Kusiro2427d":-747.0,"syak":1130.58,"hamadu":2353.39,"tanishi14":1155.83,"pengin":1154.7,"mnihyc":804.58,"Nari13":786.0,"Teppeii":920.1,"Altemis":90.0,"haji":1765.3,"Squirtle":783.67,"hi_watana":1209.34,"watason":578.19,"tanachu":823.09,"minagi":827.98,"ldurg180120":157.63,"gaudi08":810.21,"ogit":870.22,"tantakatanmen":1317.65,"cherry7kurai24":1588.37,"yapoo":1196.8,"kurihiro":1079.05,"tatt61880":1649.65,"QWYNG":1600.0,"hrynb":1600.0,"Rudy69":2112.67,"s18ti070":1329.31,"yash2406":1181.99,"square1001":2527.46,"gvastash":1734.58,"Shourov":1080.0,"urachi0826":781.06,"myoi0905":1045.14,"lyoz":2070.63,"punipuni":908.71,"Yuki_Utaai":1366.66,"radoslav11":2332.65,"issan":200.38,"yotaiyo":724.93,"HayatoY":895.84,"bbforest54":633.03,"rob_in_1":1078.42,"tsjmt":1427.33,"ussef_abdallah":720.0,"hornistyf":1250.21,"gmstev":1002.17,"jaza":232.58,"hirosuzuki":1623.8,"MohamedAhmed04":1303.09,"sugdx":1869.91,"aralsea":1106.87,"Bodo":1998.53,"Kanekoren":-222.0,"alice060318":771.63,"phyllo":1650.26,"opfer":836.72,"daut":1204.76,"plab0n":524.26,"miubook":1600.0,"Siry":1111.83,"yta_smh17":1563.75,"physsy":1600.0,"Ryuk":551.62,"wisteria0410ss":1818.09,"black":131.0,"Daili":1165.52,"gntrua":1187.0,"ymduu":1271.37,"Hide1204":1329.0,"treeone":2075.08,"numberes":943.32,"yosho":1154.42,"ekn147":1600.0,"manasjoshi":1600.0,"kuroooo":524.73,"nt1010":213.92,"hocky":1592.95,"tatsuya0619":974.46,"shkgn24":536.34,"waidotto":1441.87,"yukikakkkokari":-236.32,"bachibachiman":523.91,"mickey_1024":664.15,"Top_tosshi":-246.35,"zerokugi":2647.52,"kenimo":2076.26,"noimi":1984.62,"nakio0308":310.35,"lichang0928":1600.0,"Danylo1999":2171.96,"leign":2391.36,"Altair626":1106.09,"ts4mr":1096.68,"inaba3":853.42,"Bondo416":762.03,"josdas":2243.0,"congthanh2000":899.9,"kyosuke0924":995.87,"yuki1997":1424.55,"FLDutchman":1667.74,"isa_rentacs":1603.19,"chocopuu":1246.2,"ks2m":1128.37,"Atria":235.48,"sw8iyla":1600.0,"KazukiMH":1572.03,"k_kiri":515.52,"assy":2139.66,"daison":1050.0,"kid_drill":1600.0,"robertv":1684.3,"totechite":1600.0,"tubuann":1956.8,"biggar":658.28,"Lithium":1291.36,"kota0127":632.67,"mshcherba":1871.54,"mumumucoder":446.62,"Doneru":808.82,"wag_k":619.03,"woodline23xx":1265.46,"daiki290":760.0,"bgpat":364.4,"kiseichu":969.0,"y011d4":1288.7,"Kiri8128":1843.05,"hanato":666.39,"pirop":-345.59,"yutala":875.47,"aniket9465":1593.24,"shichinomiya":1394.12,"jinenjyo":171.47,"oyas":1851.22,"T49E2":1224.23,"fibomomo1":705.25,"knohkw":987.84,"Teaki":543.63,"ikazuya0201":951.23,"hattarist":994.49,"c_r_5":1105.9,"stan255":1382.32,"KoyanagiHitoshi":746.08,"tangent0723":1520.35,"Tatsunosuke":658.0,"ryoryoryo111":1399.63,"fuu32":995.14,"prolog":1177.36,"Apppp11":1400.37,"waffoo":1188.26,"camypaper":2746.52,"M_s_Y":1070.0,"syarai":1567.06,"alme1006":159.54,"dn6049949":1090.89,"popolo5555":1262.76,"tada":768.77,"akash1509":1333.83,"pierre":621.55,"shitoriron":1471.26,"nhara551":589.64,"ha15":1776.24,"wdyhy":2193.27,"harmokey":1569.7,"masa002":1928.29,"divinediscon10t":807.37,"wkb89_":1616.0,"tm1783":133.75,"fetburner":1502.0,"katou_113":1600.0,"shot":1521.6,"kent4989":1600.0,"mizinnkotaisa11":773.89,"mayayutaka":1152.5,"kokubun0293":1232.38,"alumina8":956.58,"Momiyama":245.09,"kutimotitokura":1781.72,"NeonSky":1678.51,"climpet":2767.01,"yuhei":1342.86,"mizuki":1324.03,"mathda1":1446.18,"frog2002":704.8,"shimomire":2342.55,"meshanya":2303.38,"hrbt":1240.06,"hirata0517masato":1312.5,"su_565fx":1253.08,"numatanumanuma":508.05,"MikeMikett":1830.37,"phanta_stick":1140.4,"RMQ":1514.05,"WB_hacker":251.01,"cm43punk":907.01,"mhi3":863.88,"crame2":318.14,"mukku":1413.4,"naoki2016":2004.91,"ibuki2003":1295.33,"sk0":1402.17,"SWAco":837.75,"diagon_alley":99.0,"socha":1401.9,"aaa_bbb":652.6,"THERMITER":279.31,"yamate11":1482.42,"koyumeishi":1994.58,"yehara":1717.58,"Yama24":767.38,"bg02":1600.0,"nb6u7":1110.29,"thienchidh":1600.0,"CleyL":1067.94,"gyoubu":1600.0,"unyacat":454.04,"edamame88":1207.49,"BALSsearch":1113.64,"DDos":1861.82,"kdskvr":1097.85,"zwu_2017010896":616.45,"rsk0315":1655.28,"mirac":2048.0,"orc17":1211.67,"yuki2006":1229.23,"eomole":1476.98,"AlaminJust":1360.01,"tkeita":1197.5,"silopy":866.74,"Tokisan":1480.56,"nuts":1329.45,"kojingharang":1641.53,"ykmaku":1207.8,"TMJN":1757.3,"tsutaya":966.5,"toku":1225.61,"Ryo_145":622.07,"hiromi_ayase":1897.73,"noman":1172.55,"pekempey":2261.57,"abeker":2181.07,"wdkkou":809.14,"emanon001":1104.0,"reluka9339":927.78,"ArturSocha":1460.76,"amotoma3":1964.57,"masakun":834.16,"hamray":1106.37,"carrotRakko":1225.39,"ruterute1":1701.8,"naka24440":1600.0,"ikzm":1600.0,"shiftpsh":1600.0,"Noiri":745.73,"saisurya027":790.37,"cutmdo":1476.19,"inaba00032":1183.05,"tomo0608":1043.12,"devarshi09":917.96,"reitetsu":621.35,"umison":1166.14,"Ka_rin_tou82":353.48,"Bobobo":-1030.0,"habroptilus":1117.75,"huma17":1101.69,"ush":2183.3,"orca":1516.95,"tohliheng":1600.0,"noriok":1170.59,"hhirai":1203.75,"skym":661.7,"Urlieonthe4":1132.02,"TomA":876.83,"bombra108":1151.91,"Gear":1708.17,"aaabbbcccddd":1757.15,"tonny":1600.0,"jimmyzhang":665.01,"butanokakuni":1102.43,"sjc061031":1250.75,"sasakama2406":665.26,"Yukly":1480.91,"Shiro_S":360.29,"on0z":1600.0,"kei_q":1214.29,"miyub":284.2,"tea437354":748.74,"zhouzhaojun":1130.37,"yukim":2190.57,"hato_roll":1475.46,"Samejima00":298.0,"girugamess":793.31,"ayumuhack":1188.61,"r1825":1187.99,"rmizuta":1196.2,"daleksprinter":1283.59,"matsuhiro55":171.11,"mikikun1959":853.03,"kopricky":1373.76,"ir_1st_vil":529.89,"solidhtwoo_2":1600.0,"object_1037":552.65,"V_Melville":1241.43,"mmxsrup":1702.48,"ikeha":1108.89,"tomoyuki7192":372.82,"tk555":1094.29,"miyahan":623.44,"lixinran":1350.18,"fushime2":930.96,"ponpon05":1364.65,"CREEPER_":1066.51,"NAH2005":1000.41,"OpenTheWindow":-124.11,"Latixahi":672.32,"mad0":1600.0,"hiro116s":2004.96,"a_key_bako":1091.78,"dsytk7":1429.76,"Jonki324":594.46,"himyzk":285.87,"ry3s":588.13,"mo2":1288.37,"rkaushick":390.47,"toriroro":176.02,"kMotz":856.94,"yakamoto":1571.4,"OribeYasuna":839.54,"akiozi":617.84,"ktr216":1441.8,"hima_megane_":1600.0,"eikani":1515.13,"yaketake08":2243.66,"kenmo":719.27,"jellyfish":1074.57,"plcherrim":1643.97,"YujiSoftware":1044.74,"decrypto":1364.3,"penkuririn":756.12,"eicge6tgns":1018.61,"zaki1236":579.13,"BlahDuckling747":1222.35,"sugibad1412":755.65,"zhuhanhua":574.08,"JokerPoker":1905.78,"I_am_stupid":1782.37,"matsugen1234":813.49,"mkiken":1661.75,"Fukumoto":548.99,"skrts13":1058.36,"Dokudami_chang":117.09,"yakimo":754.25,"Shaketan":808.74,"kkktym":646.91,"eiya":2076.79,"lduwuziwei":1600.0,"thickdrgon":839.56,"waccho":1485.47,"mtst1":734.43,"masas1991":1461.0,"Leader_27":1137.7,"iikuni_bakuhu":1051.07,"TateyamaKaito":1205.19,"yandy":879.74,"arc":1231.24,"n4o847":1501.37,"qvv3rtj":654.0,"TakaakiUmedu":1580.21,"shin_12":349.96,"empty_fine":820.73,"takoda":1085.3,"r1705":1369.25,"xyz600":1751.04,"phocom":1167.01,"saio4016":958.8,"yukatayu":1638.58,"ttrr":849.81,"kam1tsur3":985.0,"nicolen":548.34,"hanyuwei":1494.36,"NightRaven":1415.45,"mito314":536.96,"kazunetakahashi":2027.96,"ysokjkr":462.0,"kuisiba":534.83,"blue_jam":1861.47,"Igor":1141.0,"w80707":650.93,"takaten":1381.17,"fangyoule":2542.72,"integralyamada":1459.56,"ixmel_rd":2420.63,"yniji":392.0,"dj_pebble":994.28,"Ravenoux":751.84,"nmnmnmnmnmnmnm":1852.63,"NishiYuki":700.4,"newsneeds":821.31,"Eric_hoo":1472.05,"Wa6Ln":569.41,"kosuke1012":675.76,"inayoshi_1026":1132.12,"funnything":1465.89,"compass":1172.17,"sca1l":1404.52,"ckr_sdj":1600.0,"harshhx17":296.0,"kametaro":735.23,"goryudyuma":1887.49,"k111111":1479.15,"dragoon":2654.27,"not":2464.42,"drken":2409.83,"gumfum":1388.11,"kk0195736":427.12,"matsuki1045":771.95,"Aman0312":1441.06,"shugo256":1003.68,"toutatsu":662.39,"a1i":1390.82,"divyansh_soni":563.39,"rimmoc833":992.6,"Tesla":367.79,"samarth491":1532.95,"code00one":1058.14,"Haruyuk1":1214.16,"CharlotteL":1485.32,"Div9851":1758.47,"GidroOttenok3797":1600.0,"tako_39":795.67,"kawanishi9726":631.21,"ugis":896.35,"Badlylucky":1221.1,"udaynain":977.96,"shoham9":1600.0,"hiroHirohiroh":658.08,"KTurA427":866.88,"gamino":675.03,"asprova":1600.0,"peria":1490.08,"grun1396":963.55,"moke":500.89,"JWoong148":2281.62,"autotaker":2044.42,"vivek_zi":736.0,"fp563":976.51,"machy":2009.34,"gott":805.13,"TowersofHanoi":1600.0,"utime":1115.81,"hikalium":1058.88,"Nightmare05":1504.57,"swapnil07":989.0,"paulocezar":1650.15,"lavender730":1379.56,"zaqi5678":322.34,"noribentooooooh":1286.83,"amebicComber":1133.04,"xmaccode":412.19,"blcn":1417.29,"katostar":866.19,"okaduki":1975.68,"shiita0903":1450.13,"kdlvklv":525.81,"laonianrencaozuo":1406.32,"skjmp":1340.67,"suiso":128.91,"wakasa511":993.47,"gomatamago":825.36,"forest3":488.86,"yuandue":647.27,"mohibur":650.0,"nekoder":896.65,"ei0124":623.09,"heisay":832.86,"SpokenLib":1474.24,"WEDGE0512":1202.06,"yetnone":1383.29,"kimura1821":893.52,"smina":818.39,"neruneru":562.0,"realbe02":1542.0,"dn154":1212.26,"sharatsachin":1600.0,"noshi91":2354.29,"wangjue":902.74,"Misaki384":659.98,"epopaca":1253.14,"Marty_9800":837.53,"yoko":1127.33,"joy09272002":2317.89,"renoyu":902.58,"C622swallowangel":613.7,"shirara":1356.74,"mohi":953.28,"kazuhitot":1222.43,"bugger":1221.51,"primenumber":2003.67,"melpier":386.42,"satya26":1600.0,"kawasin73":1255.96,"Kou026":480.73,"luckyno9":747.77,"QCFium":1715.34,"SHOW47":1600.0,"sei1tani":513.24,"yuzupom":1507.04,"Niemuuu":1600.0,"kitokun":274.2,"trfv":804.01,"iica":1661.43,"sincerely2you":925.19,"tato":1079.58,"nayuta13":325.04,"Doarakko2049":774.82,"liouzhou_101":2232.27,"topaz13":861.8,"noko206":787.51,"pyu666":543.59,"jannkennshitai":1004.64,"cormoran":1764.93,"tralalala":1917.87,"cyan":1573.15,"iruka":873.47,"Tomii9273":1151.15,"umezawatakeshi":1402.84,"motigome":1375.03,"puyopop":1720.49,"Markomafko972":1404.79,"cocomoff":738.78,"kappy":174.72,"takanotume24":-524.0,"kou824":-29.13,"kujira438x":1490.13,"For_me_Tsima_is_":1275.75,"skwbc":1324.84,"matsuwo":489.16,"agridrama":1128.21,"kusa10":431.78,"quhengyi11":1922.18,"tomotomo":878.27,"kotobuki":1295.08,"rahilmalhotra001":1543.8,"nadare881":1561.25,"ritick":1600.0,"tomoki_kikuta":1600.0,"omygtsux":865.02,"brijeshpanara24":1600.0,"chahan69":1545.07,"etyu":1805.14,"kusano":2044.29,"Cashimom":493.32,"ikea0064":1164.35,"karasuex54":709.81,"cumene":569.0,"jjjjjjjtgpptmjj":647.02,"btk15049":2522.36,"ek135624":499.03,"Valkyrja":800.38,"Ssn_sarang":1600.0,"myun":1600.0,"overcoming":870.6,"tlwpdus":2865.92,"hirono999":346.0,"tubotu":1218.53,"ham54321":1600.0,"kou":1517.01,"M83":1529.38,"ashiknur":413.47,"tomy":1222.66,"mirachu":1144.31,"k0kubun":1276.63,"NicholasPatrick":2112.12,"nham":1600.0,"MuraTetsu":545.0,"M_Saito":1803.96,"zekkiyoumachine":59.09,"MiSawa":1600.0,"awayan":1182.71,"kuretchi":1357.04,"ogura01":1350.74,"hanyutrans":1212.0,"hukamati":240.1,"shugo1107":657.43,"dsa":920.14,"arounderstand":998.01,"hdottaka":1600.0,"sekiyn":613.61,"creed983":1104.69,"mizukurage":1313.53,"BaseOutside":394.16,"FourmiSushi":625.39,"matsu7874":1742.02,"tky_ymr":235.76,"mi2":188.53,"wtnk0812":1001.87,"akovski":2196.11,"hoo89":804.43,"penicillin0":694.0,"eigh8_t":1039.87,"odasatoshi":971.75,"mengzhao":1175.68,"to2":705.42,"rg99":1600.0,"xeno1991":1210.92,"letranger":1376.54,"jack007zz":1600.0,"yukinea":1600.0,"teacat":238.0,"shun65":314.29,"poo_mrtk":919.94,"yokoteru":-0.13,"multiple_gamma":680.37,"uenoku":1676.76,"tomboftime":1092.17,"xlfs":54.0,"ill":1124.75,"wikrsh":1065.87,"mochi32":1600.0,"phidnight":2717.19,"yiqi2qi":533.86,"yosswi414":1092.77,"sugarpoyo":1513.21,"es135":720.23,"wafrelka":2507.05,"mochi_yassy":292.24,"youx":1239.93,"NKH123":1600.0,"Iamnoob":1181.72,"tsuzuki":1414.95,"pps":1052.26,"no15_renne":1697.72,"BSC_exaltedorb":524.58,"shirokumaA":1600.0,"ToshiroYanagi":945.62,"mizoguch":966.88,"ysuzuki5321":1294.32,"hundo":-16.6,"chudanu":1213.98,"ryuichi1208":-345.0,"TeT0_Lu":228.13,"douchebag":1600.0,"WW228":1108.73,"sg08":766.74,"glycine":1140.0,"kt_soup":-26.0,"manabu":687.31,"chador":1600.0,"infrub":2522.0,"guogai":1600.0,"capstair":1600.0,"orca1732":414.24,"honjet":1600.0,"Scosa":1334.43,"flowlight":2405.03,"hos_lyric":2945.37,"yurufuwachan":710.53,"yoshiki1123":563.4,"KUMAWO":887.63,"kou_7215":91.95,"tayu":535.77,"kunito777":-181.9,"tanba":986.37,"bowwowforeach":1135.62,"uts45":1129.56,"yefllower":1600.0,"okadataku0903":521.81,"micklo":1048.47,"im3":606.47,"Linus":1409.39,"yaxkinasx":1149.16,"tkdshi223":498.12,"mamime19":967.27,"npz35":1307.59,"kosakkun":1730.29,"reid_tuat":404.19,"kazuki2105":165.89,"nooka":1479.92,"smon":860.26,"T14":1600.0,"BEPHL":533.69,"kayarr":336.51,"TwinkleSky":356.92,"progfay":878.45,"bublin":714.02,"Yoshiakira":712.55,"idaten":1379.53,"tyataro":361.44,"C7BMkOO7Qbmcwck7":1059.74,"takestoone":911.1,"sakihiro":-337.0,"hiratai":1618.84,"drmaschine":452.02,"mooom":-169.85,"tsutarou10":1081.19,"Nafmo2":1198.38,"ajinori":1335.45,"wakimiko":761.57,"Nanashino":78.29,"tako0218":1157.58,"frozen":1550.48,"shar18":987.17,"Itatatu":577.96,"CatDog456":699.94,"Rikuya6":485.69,"keita27":1285.43,"unipota":542.62,"hapdap":1089.3,"fastapple":477.52,"ms5":73.63,"dAi00":1420.1,"BlackBracken":674.92,"nakario":705.56,"PhilisPaxil":646.64,"amano":2114.64,"ketancho":618.06,"YamaguchiT":1275.7,"odan":1440.54,"libra9z":1378.89,"Mr_Wu":1600.0,"txmy":1248.06,"shahraaz":592.42,"shizukacode":546.41,"mikiyana7707":-178.95,"yudedako":1697.35,"mittalshubham":1190.76,"yuiop":1703.53,"yuyu12":418.19,"zwu_2017010444":440.26,"hilary":431.71,"banquet":618.81,"p_km":1491.29,"oyassan":470.46,"rk957019":1181.0,"sarugami":327.37,"foradqwert":511.63,"Roughcut":1600.0,"rainy2041":395.72,"ruu_413":848.5,"ryouri":1246.19,"saharan":1943.82,"toasa":1600.0,"blackduckn":582.67,"xish":1444.03,"fockl":1254.36,"DFNasutarou":1133.47,"myanta":1406.04,"natu":518.75,"sui_null":1600.0,"fortoobye":1731.5,"butterfly1026":1094.43,"stan":1224.32,"aguroshou":1168.98,"fujiyama":470.06,"capy":711.68,"nemurin":1600.0,"moritan0000":1057.39,"phykmqqq":1230.41,"Eran":2236.05,"sanesuke":1002.05,"yoshiyasu":-1030.0,"inletsun1":1003.8,"Tosachi":678.31,"takapy0210":-460.0,"biones":759.6,"yuki228285":354.53,"hinatades":1600.0,"loongtail":732.03,"ryboc":327.39,"masay":1327.0,"noboru":320.14,"gbis36":2018.95,"amata1219":1600.0,"tabinessie":1289.56,"Remonn":880.49,"KUNIO_NAGAI":572.2,"hmdtarako":542.48,"llll_":1659.17,"tyoukaku314":890.53,"aknory710":1317.09,"gobou0516":173.85,"heysan":1029.58,"tengu_of_kurama":-76.0,"mohei":1131.21,"yoshiki_shino":707.31,"harasho0103":147.18,"vivekcrux":1351.13,"ken0502":1031.84,"outlook":-55.95,"Darshan":1600.0,"zilch":1600.0,"Sonono":184.58,"pasyama":303.47,"Rinscg":471.68,"rohna":475.48,"kumojima":1600.0,"ymch1905":1437.18,"tdyydt":696.27,"Kiterai":753.73,"ryo111":602.74,"takepansan":305.71,"tanigawat":1600.0,"k11200070":406.0,"dkrqr":767.94,"funwarioisii":265.95,"wkkautas":1324.59,"rufy":1600.0,"harshit601":962.55,"azbrugby":1570.01,"sansaqua":1279.7,"Lafleur":1139.42,"KiriMaru":1600.0,"akbar1214":119.0,"just_soso":1555.26,"saikoumi":1428.66,"ina_yuzen":1638.79,"tetIapot":1600.0,"silmin":1600.0,"albus":1600.0,"komichan":1600.0,"sibi77":556.11,"hituzi":723.22,"You53":727.43,"wleung_bvg":1793.65,"shiromashiro":1.53,"kawatom":604.87,"OP_mouse":1600.0,"phos":431.54,"darjeeling":726.19,"yusuke0518":892.03,"quantum0":1600.0,"tokotoko7777":292.84,"banban":975.58,"takahashi00":942.24,"m1m4d":-67.0,"hironeko21":1600.0,"honake":1075.57,"gorugo":1600.0,"s4y4":610.07,"ysfk":801.17,"yuhi0735":43.26,"tomu106":759.93,"uzzy":1741.03,"sima0222":912.15,"kcidb6Hq":301.79,"mmatthew_43":541.15,"horiso0921":1615.0,"Moscwa":903.96,"andrey_efremov":2349.22,"koko78787":423.57,"tks_fj":1059.6,"tk_hacked":1074.67,"Nocks_on":734.42,"i4e":1255.0,"tani":316.19,"lovehotel246":780.66,"intst30":-225.0,"Nath":382.35,"bokuzin":58.59,"anshika":1600.0,"rennaka":1600.0,"MZKi":103.39,"copy":1600.0,"huzhejie":956.41,"ykm":1600.0,"myutetit810":114.32,"Despair2718":1600.0,"chenrundong":1600.0,"take_10":-390.95,"scau_lok":1566.64,"kinta122":932.42,"pashipon":1600.0,"kekenx":330.5,"thas":1600.0,"kan24":463.51,"Hiekichi":1600.0,"Fluvius":-310.0,"peach2357":381.0,"side":777.39,"aleutra":1249.92,"IceKnight1093":1718.47,"ikuya_sam":403.25,"zero0yumechi":905.67,"bust726":-34.0,"hrokamo":1600.0,"zxc_identity":735.02,"wider9":1600.0,"hijili":382.0,"shadowatyy":2468.13,"Fuyume":74.15,"berthemorisot":1600.0,"ryuNagai":541.24,"Hashioki":-384.0,"nwin":2234.14,"lly_japan":1600.0,"oich":1600.0,"djcafe":1600.0,"lqybzx":2282.0,"estis":404.4,"maruii":1600.0,"NS601023":928.5,"hejun":1600.0,"jirlock":979.71,"popontta":184.89,"kumatako":75.04,"berlysia":1090.47,"Napatnicky":545.61,"shoy75":328.0,"Ace_02":1278.41,"sharmajatin741":1262.53,"fusen":369.6,"neetsdkasu":919.86,"Cassin":99.0,"gomamitu":70.72,"hatomuru1":1600.0,"notkzk":429.03,"reiva5":885.23,"tour1st":1612.29,"genzai":394.26,"tironaka":898.43,"botacat":-271.0,"hirota_tech":386.79,"jorujio":1600.0,"matsunaga21895":1600.0,"suz64":226.3,"zwu_2017010476":411.12,"MaRos":892.27,"tasmeemreza":1981.34,"Midoca":292.25,"sifue":856.09,"dynabw":407.54,"yyxchn":-248.0,"chris5502":706.51,"jhuim08":-79.94,"cwystc":2305.86,"PG_23":-43.04,"kaname":637.41,"Lilkoke11":462.03,"asert":-147.0,"kinokino":154.17,"ms22nvmbr":1600.0,"yuma_y":1600.0,"NakamotoJiro":1600.0,"Efutei":550.22,"mzthr78":480.87,"Moryshun":1600.0,"asupar_eom":418.48,"Y_dev":887.0,"pekohara":-587.0,"Tategami":889.95,"nishipy":31.0,"zwu_2017010630":520.68,"akky":751.53,"jack":-95.39,"PAF00423":1600.0,"a45823":613.34,"MB81":1673.46,"RY_0528_RY":-8.29,"masaaaaaaaaaa":1600.0,"atFFFofK":937.2,"DucPro":1600.0,"keimy":804.2,"Merugon":1600.0,"hogetaro":429.21,"haramaki":1600.0,"hyoutann":325.32,"crize":541.05,"yamashita_1224":432.02,"isse0518":1600.0,"AmdSadi":1031.41,"sampass":1319.0,"takoagemat":-85.0,"stardust":155.0,"Jon3":1560.49,"diehard1920":1600.0,"ckxkexing":1600.0,"Surus":-227.3,"nxtgear":532.43,"naum":1600.0,"crazy__1234":1600.0,"tassu619":-210.31,"ikkyu3":-243.63,"ohken":606.62,"hafiz_samrat":1100.38,"haha159":1600.0,"ababa":279.85,"wahahawa":777.56,"Hum1060":191.85,"nonsensi":1600.0,"fishfree88":1600.0,"satoshii":998.7,"JKJeong":1395.07,"kurokuro96":179.98,"hanori":249.91,"classcast":1600.0,"kakinoki8":521.19,"faula":1600.0,"cheshirecoder":1174.0,"AndyMo":1375.66,"at278Mt":1600.0,"kangzenan":1600.0,"TomoYama9":-192.32,"hashiryo":1602.53,"mathmiki":76.0,"opq":1600.0,"zwu_2017010687":620.46,"satoshi_f":905.67,"tnktemp":913.43,"mukadenodaiou":1247.85,"Hannibal_Lector":1600.0,"hechima":1600.0,"flyingFrozenUdon":1079.48,"HMaekawa":854.05,"watmeron":1600.0,"manji":1600.0,"HoangTheAnh":-176.0,"kyusque":-175.21,"yakata66":1078.5,"tyty0822":270.56,"sevenazuki":1600.0,"takerun":7.74,"Fulltea":1113.49,"ghostfly233":1600.0,"trucvy05062003":1600.0,"panole":1926.33,"pink_rabbit":1922.41,"starve724":1600.0,"KobeDuu_":845.0,"yassie":703.28,"ogino":1991.59,"rakuko":-139.08,"bismuth":318.14,"fujarenpaw":1600.0,"takoyakiusagi":110.76,"lolohfqsfqhfq":1600.0,"Ch_zaqdt":277.6,"black38":1600.0,"zwu_2017010440":871.64,"Pagliacci":674.0,"Nil":1600.0,"hytzongxuan":1765.6,"LorenaMaria":747.29,"nononaga":663.3,"keitanxkeitan":1237.02,"cexen":1412.65,"somebody":-296.0,"re3turn":1600.0,"pushpendra1997":1587.79,"withoutpower":1413.01,"zhou2003":1521.48,"taichin":-493.0,"revas09":1212.07,"llgyc":1466.86,"aochan":631.46,"y_immortal":1746.27,"ryora0723":-473.07,"Gibson":1600.0,"Stingray":-365.93,"Khmer":321.32,"craftsman":1600.0,"jyoban":816.42,"wangz3859":-99.0,"omu58n":99.0,"sickhack4989":342.64,"prm0130":-599.8,"codercjh":1600.0,"foxykodai":198.14,"sunyx":1600.0,"hocashi":257.0,"agoyr":239.31,"fadi57":311.79,"mizuame":-935.0,"gtuif":1600.0,"huukiethk2804":1600.0,"shanky":1933.79,"masoomraja94":1600.0,"yuukiprivate":440.15,"tsun23":1600.0,"morisita611":-221.06,"mkgrei":1522.0,"bella0708":129.74,"zzuzxy":1163.38,"kayaminm7":1132.16,"wjx16120004":-268.92,"huas_dengyin":921.89,"hiro_ki":1600.0,"toan0105":1600.0,"ryupy":-18.37,"DenDenDe":1600.0,"Murasame_HC":1287.0,"chien03082003":-725.0,"yamanashimu":-555.0,"s_h_shahin":1642.66,"Ann_G_A":-345.84,"codehunter":1337.0,"ugly2333":2548.53,"horoscope":1600.0,"Kize":313.2,"koudai":390.69,"zjp_shadow":1941.29,"chenchen":658.16,"AhmedMokhtar":1600.0,"umikawa":1600.0,"shadatsk40":1600.0,"hypergori":1600.0,"PSKP_95":1600.0,"zxz666":490.99,"hikario2kamu":-354.0,"stringray":1187.58,"SaBaTa6060":1600.0,"Rafeed":1600.0,"pit611kepo3054":693.01,"mtsuru":1600.0,"kuroni":1907.25,"thnam":639.0,"yuko1658":1600.0,"miss_me_9":1081.7,"marumine51":724.37,"indrajit1":1600.0,"Ismail_A":408.66,"alanwanga":334.82}